Workbook

Sheet How to use
A1: Complaints Register – how to use
A2: Firm: [Insert firm legal name] | Register owner: [Insert name and role] | Last reviewed: [Insert date]
A4: How to use this register
A5: This register is part of the KMS compliance framework. The policies that refer to it expect it to be kept up to date from your first day of trading: the FCA judges a firm on the records that show its policies working in practice, not on the policies alone. A policy without its supporting records is unlikely to withstand FCA scrutiny.
A6: Yellow cells containing text in [square brackets] are placeholders – replace them with your own details. Green header cells are column headings; do not delete a column unless the guidance for that column says you may.
A7: Green “OPTION” rows mark rows that only apply to particular regulated activities. Keep the rows under an OPTION label if your firm carries on that activity; otherwise delete the OPTION row and the rows beneath it, down to the next OPTION row. Each option stands alone.
A8: Drop-down lists are provided for consistency. The underlying lists are on a hidden sheet called “Lists” – unhide it (right-click any sheet tab, Unhide) if you need to change them.
A9: Keep this register securely, restrict access to the people who need it, and keep it for the retention period set out in the relevant policy and your Data Retention Schedule.
A10: What to record
A11: Record every complaint – any oral or written expression of dissatisfaction about our financial services alleging financial loss, material distress or material inconvenience – on the day it is received (or by the end of the next business day). The DISP time limits run from the date any member of staff, or anyone acting for us, first received it.
A12: Deadlines
A13: The register calculates: the summary resolution deadline (close of the third business day after receipt); the eight-week final response deadline; and, for payment services complaints, the 15-business-day deadline (35 business days in exceptional circumstances). The business-day formulas do not exclude bank holidays – check dates close to bank holidays. Delete the payment services columns if you do not provide payment services.
... A17: Since 19 June 2026 data protection complaints must be acknowledged within 30 days. Tick the data protection column so the acknowledgement deadline is calculated.

Sheet Complaints Register
A1: Complaints Register
A2: Firm: [Insert firm legal name] | Register owner: [Insert name and role] | Last reviewed: [Insert date]
A3: KMS guidance: Record every complaint by the end of the next business day. Deadlines calculate automatically from the date received. Delete columns L, P and Q if you do not provide payment services.
A4: Complaint details | M4: Deadlines (calculated) | S4: Response and outcome | Y4: Learning and Ombudsman
A5: Ref. | B5: Date received | C5: Received by | D5: Channel | E5: Complainant name | F5: Customer / representative | G5: Regulated activity / product | H5: Complaint category | I5: Summary of complaint | J5: Vulnerability / adjustments | K5: Data protection complaint? | L5: Payment services (PSRs Parts 6/7) complaint? | M5: Acknowledged on | N5: Summary resolution deadline (3 business days) | O5: Final response deadline (8 weeks) | P5: PSR deadline (15 business days) | Q5: PSR exceptional deadline (35 business days) | R5: Data protection acknowledgement deadline (30 days) | S5: Handler | T5: Date of final response / 8-week letter | U5: Outcome | V5: Redress (£ and type) | W5: Date redress paid | X5: Forwarded to (firm) | Y5: Root cause | Z5: Wider action taken (Corrective Action Log ref.) | AA5: Ombudsman referral | AB5: Ombudsman outcome and date
A6: CR-001 | N6: =IF(B6="","",WORKDAY(B6,3)) | O6: =IF(B6="","",B6+56) | P6: =IF(OR(B6="",L6<>"Yes"),"",WORKDAY(B6,15)) | Q6: =IF(OR(B6="",L6<>"Yes"),"",WORKDAY(B6,35)) | R6: =IF(OR(B6="",K6<>"Yes"),"",B6+30)
A7: CR-002 | N7: =IF(B7="","",WORKDAY(B7,3)) | O7: =IF(B7="","",B7+56) | P7: =IF(OR(B7="",L7<>"Yes"),"",WORKDAY(B7,15)) | Q7: =IF(OR(B7="",L7<>"Yes"),"",WORKDAY(B7,35)) | R7: =IF(OR(B7="",K7<>"Yes"),"",B7+30)
A8: CR-003 | N8: =IF(B8="","",WORKDAY(B8,3)) | O8: =IF(B8="","",B8+56) | P8: =IF(OR(B8="",L8<>"Yes"),"",WORKDAY(B8,15)) | Q8: =IF(OR(B8="",L8<>"Yes"),"",WORKDAY(B8,35)) | R8: =IF(OR(B8="",K8<>"Yes"),"",B8+30)
A9: CR-004 | N9: =IF(B9="","",WORKDAY(B9,3)) | O9: =IF(B9="","",B9+56) | P9: =IF(OR(B9="",L9<>"Yes"),"",WORKDAY(B9,15)) | Q9: =IF(OR(B9="",L9<>"Yes"),"",WORKDAY(B9,35)) | R9: =IF(OR(B9="",K9<>"Yes"),"",B9+30)
A10: CR-005 | N10: =IF(B10="","",WORKDAY(B10,3)) | O10: =IF(B10="","",B10+56) | P10: =IF(OR(B10="",L10<>"Yes"),"",WORKDAY(B10,15)) | Q10: =IF(OR(B10="",L10<>"Yes"),"",WORKDAY(B10,35)) | R10: =IF(OR(B10="",K10<>"Yes"),"",B10+30)
A11: CR-006 | N11: =IF(B11="","",WORKDAY(B11,3)) | O11: =IF(B11="","",B11+56) | P11: =IF(OR(B11="",L11<>"Yes"),"",WORKDAY(B11,15)) | Q11: =IF(OR(B11="",L11<>"Yes"),"",WORKDAY(B11,35)) | R11: =IF(OR(B11="",K11<>"Yes"),"",B11+30)
A12: CR-007 | N12: =IF(B12="","",WORKDAY(B12,3)) | O12: =IF(B12="","",B12+56) | P12: =IF(OR(B12="",L12<>"Yes"),"",WORKDAY(B12,15)) | Q12: =IF(OR(B12="",L12<>"Yes"),"",WORKDAY(B12,35)) | R12: =IF(OR(B12="",K12<>"Yes"),"",B12+30)
A13: CR-008 | N13: =IF(B13="","",WORKDAY(B13,3)) | O13: =IF(B13="","",B13+56) | P13: =IF(OR(B13="",L13<>"Yes"),"",WORKDAY(B13,15)) | Q13: =IF(OR(B13="",L13<>"Yes"),"",WORKDAY(B13,35)) | R13: =IF(OR(B13="",K13<>"Yes"),"",B13+30)
A14: CR-009 | N14: =IF(B14="","",WORKDAY(B14,3)) | O14: =IF(B14="","",B14+56) | P14: =IF(OR(B14="",L14<>"Yes"),"",WORKDAY(B14,15)) | Q14: =IF(OR(B14="",L14<>"Yes"),"",WORKDAY(B14,35)) | R14: =IF(OR(B14="",K14<>"Yes"),"",B14+30)
A15: CR-010 | N15: =IF(B15="","",WORKDAY(B15,3)) | O15: =IF(B15="","",B15+56) | P15: =IF(OR(B15="",L15<>"Yes"),"",WORKDAY(B15,15)) | Q15: =IF(OR(B15="",L15<>"Yes"),"",WORKDAY(B15,35)) | R15: =IF(OR(B15="",K15<>"Yes"),"",B15+30)
A16: CR-011 | N16: =IF(B16="","",WORKDAY(B16,3)) | O16: =IF(B16="","",B16+56) | P16: =IF(OR(B16="",L16<>"Yes"),"",WORKDAY(B16,15)) | Q16: =IF(OR(B16="",L16<>"Yes"),"",WORKDAY(B16,35)) | R16: =IF(OR(B16="",K16<>"Yes"),"",B16+30)
A17: CR-012 | N17: =IF(B17="","",WORKDAY(B17,3)) | O17: =IF(B17="","",B17+56) | P17: =IF(OR(B17="",L17<>"Yes"),"",WORKDAY(B17,15)) | Q17: =IF(OR(B17="",L17<>"Yes"),"",WORKDAY(B17,35)) | R17: =IF(OR(B17="",K17<>"Yes"),"",B17+30)
... A155: CR-150 | N155: =IF(B155="","",WORKDAY(B155,3)) | O155: =IF(B155="","",B155+56) | P155: =IF(OR(B155="",L155<>"Yes"),"",WORKDAY(B155,15)) | Q155: =IF(OR(B155="",L155<>"Yes"),"",WORKDAY(B155,35)) | R155: =IF(OR(B155="",K155<>"Yes"),"",B155+30)

Sheet Summary
A1: Complaints Summary (management information)
A2: Firm: [Insert firm legal name] | Register owner: [Insert name and role] | Last reviewed: [Insert date]
A4: Complaint category | B4: Received | C4: Upheld / partly upheld | D4: Not upheld | E4: Referred to Ombudsman
A5: Advice / suitability | B5: =COUNTIF('Complaints Register'!H:H,A5) | C5: =COUNTIFS('Complaints Register'!H:H,A5,'Complaints Register'!U:U,"Upheld")+COUNTIFS('Complaints Register'!H:H,A5,'Complaints Register'!U:U,"Partly upheld") | D5: =COUNTIFS('Complaints Register'!H:H,A5,'Complaints Register'!U:U,"Not upheld") | E5: =COUNTIFS('Complaints Register'!H:H,A5,'Complaints Register'!AA:AA,"<>Not referred",'Complaints Register'!AA:AA,"<>")
A6: Information / disclosure | B6: =COUNTIF('Complaints Register'!H:H,A6) | C6: =COUNTIFS('Complaints Register'!H:H,A6,'Complaints Register'!U:U,"Upheld")+COUNTIFS('Complaints Register'!H:H,A6,'Complaints Register'!U:U,"Partly upheld") | D6: =COUNTIFS('Complaints Register'!H:H,A6,'Complaints Register'!U:U,"Not upheld") | E6: =COUNTIFS('Complaints Register'!H:H,A6,'Complaints Register'!AA:AA,"<>Not referred",'Complaints Register'!AA:AA,"<>")
A7: Affordability / lending decision | B7: =COUNTIF('Complaints Register'!H:H,A7) | C7: =COUNTIFS('Complaints Register'!H:H,A7,'Complaints Register'!U:U,"Upheld")+COUNTIFS('Complaints Register'!H:H,A7,'Complaints Register'!U:U,"Partly upheld") | D7: =COUNTIFS('Complaints Register'!H:H,A7,'Complaints Register'!U:U,"Not upheld") | E7: =COUNTIFS('Complaints Register'!H:H,A7,'Complaints Register'!AA:AA,"<>Not referred",'Complaints Register'!AA:AA,"<>")
A8: Fees and charges | B8: =COUNTIF('Complaints Register'!H:H,A8) | C8: =COUNTIFS('Complaints Register'!H:H,A8,'Complaints Register'!U:U,"Upheld")+COUNTIFS('Complaints Register'!H:H,A8,'Complaints Register'!U:U,"Partly upheld") | D8: =COUNTIFS('Complaints Register'!H:H,A8,'Complaints Register'!U:U,"Not upheld") | E8: =COUNTIFS('Complaints Register'!H:H,A8,'Complaints Register'!AA:AA,"<>Not referred",'Complaints Register'!AA:AA,"<>")
A9: Arrears / collections | B9: =COUNTIF('Complaints Register'!H:H,A9) | C9: =COUNTIFS('Complaints Register'!H:H,A9,'Complaints Register'!U:U,"Upheld")+COUNTIFS('Complaints Register'!H:H,A9,'Complaints Register'!U:U,"Partly upheld") | D9: =COUNTIFS('Complaints Register'!H:H,A9,'Complaints Register'!U:U,"Not upheld") | E9: =COUNTIFS('Complaints Register'!H:H,A9,'Complaints Register'!AA:AA,"<>Not referred",'Complaints Register'!AA:AA,"<>")
A10: Customer service / delays | B10: =COUNTIF('Complaints Register'!H:H,A10) | C10: =COUNTIFS('Complaints Register'!H:H,A10,'Complaints Register'!U:U,"Upheld")+COUNTIFS('Complaints Register'!H:H,A10,'Complaints Register'!U:U,"Partly upheld") | D10: =COUNTIFS('Complaints Register'!H:H,A10,'Complaints Register'!U:U,"Not upheld") | E10: =COUNTIFS('Complaints Register'!H:H,A10,'Complaints Register'!AA:AA,"<>Not referred",'Complaints Register'!AA:AA,"<>")
A11: Staff conduct | B11: =COUNTIF('Complaints Register'!H:H,A11) | C11: =COUNTIFS('Complaints Register'!H:H,A11,'Complaints Register'!U:U,"Upheld")+COUNTIFS('Complaints Register'!H:H,A11,'Complaints Register'!U:U,"Partly upheld") | D11: =COUNTIFS('Complaints Register'!H:H,A11,'Complaints Register'!U:U,"Not upheld") | E11: =COUNTIFS('Complaints Register'!H:H,A11,'Complaints Register'!AA:AA,"<>Not referred",'Complaints Register'!AA:AA,"<>")
A12: Fraud / scams | B12: =COUNTIF('Complaints Register'!H:H,A12) | C12: =COUNTIFS('Complaints Register'!H:H,A12,'Complaints Register'!U:U,"Upheld")+COUNTIFS('Complaints Register'!H:H,A12,'Complaints Register'!U:U,"Partly upheld") | D12: =COUNTIFS('Complaints Register'!H:H,A12,'Complaints Register'!U:U,"Not upheld") | E12: =COUNTIFS('Complaints Register'!H:H,A12,'Complaints Register'!AA:AA,"<>Not referred",'Complaints Register'!AA:AA,"<>")
A13: Data protection | B13: =COUNTIF('Complaints Register'!H:H,A13) | C13: =COUNTIFS('Complaints Register'!H:H,A13,'Complaints Register'!U:U,"Upheld")+COUNTIFS('Complaints Register'!H:H,A13,'Complaints Register'!U:U,"Partly upheld") | D13: =COUNTIFS('Complaints Register'!H:H,A13,'Complaints Register'!U:U,"Not upheld") | E13: =COUNTIFS('Complaints Register'!H:H,A13,'Complaints Register'!AA:AA,"<>Not referred",'Complaints Register'!AA:AA,"<>")
A14: Product performance | B14: =COUNTIF('Complaints Register'!H:H,A14) | C14: =COUNTIFS('Complaints Register'!H:H,A14,'Complaints Register'!U:U,"Upheld")+COUNTIFS('Complaints Register'!H:H,A14,'Complaints Register'!U:U,"Partly upheld") | D14: =COUNTIFS('Complaints Register'!H:H,A14,'Complaints Register'!U:U,"Not upheld") | E14: =COUNTIFS('Complaints Register'!H:H,A14,'Complaints Register'!AA:AA,"<>Not referred",'Complaints Register'!AA:AA,"<>")
A15: Claims (insurance) | B15: =COUNTIF('Complaints Register'!H:H,A15) | C15: =COUNTIFS('Complaints Register'!H:H,A15,'Complaints Register'!U:U,"Upheld")+COUNTIFS('Complaints Register'!H:H,A15,'Complaints Register'!U:U,"Partly upheld") | D15: =COUNTIFS('Complaints Register'!H:H,A15,'Complaints Register'!U:U,"Not upheld") | E15: =COUNTIFS('Complaints Register'!H:H,A15,'Complaints Register'!AA:AA,"<>Not referred",'Complaints Register'!AA:AA,"<>")
A16: Other | B16: =COUNTIF('Complaints Register'!H:H,A16) | C16: =COUNTIFS('Complaints Register'!H:H,A16,'Complaints Register'!U:U,"Upheld")+COUNTIFS('Complaints Register'!H:H,A16,'Complaints Register'!U:U,"Partly upheld") | D16: =COUNTIFS('Complaints Register'!H:H,A16,'Complaints Register'!U:U,"Not upheld") | E16: =COUNTIFS('Complaints Register'!H:H,A16,'Complaints Register'!AA:AA,"<>Not referred",'Complaints Register'!AA:AA,"<>")
A17: Total | B17: =SUM(B5:B16) | C17: =SUM(C5:C16) | D17: =SUM(D5:D16) | E17: =SUM(E5:E16)

Sheet Lists
A1: chan | B1: act | C1: cat | D1: out | E1: yn | F1: ynna | G1: fos
A2: Telephone | B2: All activities | C2: Advice / suitability | D2: Resolved by summary resolution communication | E2: Yes | F2: Yes | G2: Not referred
A3: Email | B3: Credit broking | C3: Information / disclosure | D3: Upheld | E3: No | F3: No | G3: Referred – awaiting outcome
A4: Letter | B4: Debt adjusting and debt counselling | C4: Affordability / lending decision | D4: Partly upheld | F4: Not applicable | G4: Ombudsman upheld
A5: Web form | B5: Debt collecting and debt administration | C5: Fees and charges | D5: Not upheld | G5: Ombudsman not upheld
A6: In person | B6: Credit information services and credit references | C6: Arrears / collections | D6: Forwarded to another firm (DISP 1.7) | G6: Settled
A7: Social media | B7: Peer-to-peer lending platforms | C7: Customer service / delays | D7: Withdrawn
A8: Via third party / CMC | B8: Consumer credit lending | C8: Staff conduct
B9: Exercising a lender’s rights and duties | C9: Fraud / scams
B10: Consumer hire | C10: Data protection
B11: Insurance distribution | C11: Product performance
B12: Mortgage intermediation | C12: Claims (insurance)
B13: Payment services and e-money | C13: Other
B14: Investment advice and arranging
